{
    "display": {
        "icon": { "item": "minecraft:wither_skeleton_skull" },
        "title": { "translate": "al_adv.death.death_200.title" },
        "description": { "translate": "al_adv.death.death_200.description" },
        "frame": "challenge",
        
        "announce_to_chat": true,
        "show_toast": true,
        "hidden": false
    },
    "parent": "al_advancements:death/death_100",
    "criteria": {
        "unlock": {
            "trigger": "minecraft:impossible"
        }
    }
}