{
    "display": {
        "icon": { "id": "minecraft:diamond" },
        "title": {
            "translate": "advancements.alzheimouille.diamond.diamond_025.title",
            "fallback": "A little gear?"
        },
        "description": {
            "translate": "advancements.alzheimouille.diamond.diamond_025.description",
            "fallback": "Mine twenty-five diamond ores."
        },
        "frame": "task",
        
        "announce_to_chat": true,
        "show_toast": true,
        "hidden": false
    },
    "parent": "alzheimouille:diamond/diamond_010",
    "criteria": {
        "unlock": {
            "trigger": "minecraft:impossible"
        }
    }
}