{
    "display": {
        "icon": { "id": "minecraft:diamond" },
        "title": {
            "translate": "al_adv.diamond.diamond_001.title",
            "fallback": "Congratulations!"
        },
        "description": {
            "translate": "al_adv.diamond.diamond_001.description",
            "fallback": "Mine one diamond ore."
        },
        "frame": "task",
        
        "announce_to_chat": true,
        "show_toast": true,
        "hidden": false
    },
    "parent": "alzheimouille:root",
    "criteria": {
        "unlock": {
            "trigger": "minecraft:impossible"
        }
    }
}